fds/__init__.py
fds/protobuf/__init__.py
fds/protobuf/stach/MetadataItem_pb2.py
fds/protobuf/stach/NullValues.py
fds/protobuf/stach/Package_pb2.py
fds/protobuf/stach/__init__.py
fds/protobuf/stach/table/DataType_pb2.py
fds/protobuf/stach/table/HorizontalAlignment_pb2.py
fds/protobuf/stach/table/ListOfMetadata_pb2.py
fds/protobuf/stach/table/MetadataCollection_pb2.py
fds/protobuf/stach/table/MetadataLocations_pb2.py
fds/protobuf/stach/table/ReferenceFilterMode_pb2.py
fds/protobuf/stach/table/ReferenceType_pb2.py
fds/protobuf/stach/table/Reference_pb2.py
fds/protobuf/stach/table/SeriesData_pb2.py
fds/protobuf/stach/table/SeriesDefinition_pb2.py
fds/protobuf/stach/table/SeriesFormat_pb2.py
fds/protobuf/stach/table/TableData_pb2.py
fds/protobuf/stach/table/TableDefinition_pb2.py
fds/protobuf/stach/table/Table_pb2.py
fds/protobuf/stach/table/VerticalAlignment_pb2.py
fds/protobuf/stach/table/Wrappers_pb2.py
fds/protobuf/stach/table/__init__.py
fds.protobuf.stach-1.0.2.dist-info/METADATA
fds.protobuf.stach-1.0.2.dist-info/WHEEL
fds.protobuf.stach-1.0.2.dist-info/top_level.txt
fds.protobuf.stach-1.0.2.dist-info/RECORD
